{
    "timestamp": 1766125152281,
    "simuTime": 17700,
    "startSimuTime": 1766125117691,
    "batchNum": 177,
    "count": 35,
    "objs": [
        {
            "id": 100001,
            "name": "",
            "typeCode": 1,
            "roadId": 13,
            "inLink": true,
            "laneCount": 2,
            "laneNumber": 1,
            "laneTypeName": "机动车道",
            "angle": 228.86,
            "speed": 16.92,
            "Speed": 60.9,
            "size": [
                4.54,
                2.02,
                2
            ],
            "color": "#A0A0A4",
            "x": 58.69,
            "y": 161.25,
            "z": 0.0,
            "xOrig": 457529.85,
            "yOrig": 2711220.44,
            "zOrig": 0.0,
            "longitude": null,
            "latitude": null,
            "eulerX": -2.42348,
            "eulerY": -2.42348,
            "eulerZ": -2.42348
        },
        {
            "id": 200001,
            "name": "",
            "typeCode": 1,
            "roadId": 5,
            "inLink": true,
            "laneCount": 2,
            "laneNumber": 1,
            "laneTypeName": "机动车道",
            "angle": 48.87,
            "speed": 17.94,
            "Speed": 64.6,
            "size": [
                4.73,
                2.09,
                2
            ],
            "color": "#FFFFFF",
            "x": -489.2,
            "y": -324.4,
            "z": 0.0,
            "xOrig": 456981.96,
            "yOrig": 2710734.79,
            "zOrig": 0.0,
            "longitude": null,
            "latitude": null,
            "eulerX": 0.71781,
            "eulerY": 0.71781,
            "eulerZ": 0.71781
        },
        {
            "id": 200002,
            "name": "",
            "typeCode": 2,
            "roadId": 5,
            "inLink": true,
            "laneCount": 2,
            "laneNumber": 0,
            "laneTypeName": "机动车道",
            "angle": 51.16,
            "speed": 14.11,
            "Speed": 50.8,
            "size": [
                12.1,
                2.54,
                2
            ],
            "color": "#FFFFFF",
            "x": -538.36,
            "y": -371.88,
            "z": 0.0,
            "xOrig": 456932.8,
            "yOrig": 2710687.31,
            "zOrig": 0.0,
            "longitude": null,
            "latitude": null,
            "eulerX": 0.67785,
            "eulerY": 0.67785,
            "eulerZ": 0.67785
        },
        {
            "id": 200003,
            "name": "",
            "typeCode": 1,
            "roadId": 5,
            "inLink": true,
            "laneCount": 2,
            "laneNumber": 1,
            "laneTypeName": "机动车道",
            "angle": 51.21,
            "speed": 14.85,
            "Speed": 53.45,
            "size": [
                4.22,
                1.89,
                2
            ],
            "color": "#A0A0A4",
            "x": -549.63,
            "y": -375.87,
            "z": 0.0,
            "xOrig": 456921.53,
            "yOrig": 2710683.32,
            "zOrig": 0.0,
            "longitude": null,
            "latitude": null,
            "eulerX": 0.67706,
            "eulerY": 0.67706,
            "eulerZ": 0.67706
        },
        {
            "id": 100002,
            "name": "",
            "typeCode": 2,
            "roadId": 13,
            "inLink": true,
            "laneCount": 2,
            "laneNumber": 0,
            "laneTypeName": "机动车道",
            "angle": 228.88,
            "speed": 12.58,
            "Speed": 45.3,
            "size": [
                11.44,
                2.27,
                2
            ],
            "color": "#EEAD0E",
            "x": 124.04,
            "y": 223.74,
            "z": 0.0,
            "xOrig": 457595.2,
            "yOrig": 2711282.93,
            "zOrig": 0.0,
            "longitude": null,
            "latitude": null,
            "eulerX": -2.42387,
            "eulerY": -2.42387,
            "eulerZ": -2.42387
        },
        {
            "id": 200004,
            "name": "",
            "typeCode": 1,
            "roadId": 5,
            "inLink": true,
            "laneCount": 2,
            "laneNumber": 0,
            "laneTypeName": "机动车道",
            "angle": 53.46,
            "speed": 13.78,
            "Speed": 49.6,
            "size": [
                4.37,
                1.95,
                2
            ],
            "color": "#EEAD0E",
            "x": -571.01,
            "y": -398.15,
            "z": 0.0,
            "xOrig": 456900.15,
            "yOrig": 2710661.04,
            "zOrig": 0.0,
            "longitude": null,
            "latitude": null,
            "eulerX": 0.63783,
            "eulerY": 0.63783,
            "eulerZ": 0.63783
        },
        {
            "id": 100003,
            "name": "",
            "typeCode": 1,
            "roadId": 13,
            "inLink": true,
            "laneCount": 2,
            "laneNumber": 1,
            "laneTypeName": "机动车道",
            "angle": 228.86,
            "speed": 16.32,
            "Speed": 58.76,
            "size": [
                4.67,
                2.07,
                2
            ],
            "color": "#A0A0A4",
            "x": 100.16,
            "y": 197.49,
            "z": 0.0,
            "xOrig": 457571.32,
            "yOrig": 2711256.68,
            "zOrig": 0.0,
            "longitude": null,
            "latitude": null,
            "eulerX": -2.42348,
            "eulerY": -2.42348,
            "eulerZ": -2.42348
        },
        {
            "id": 100004,
            "name": "",
            "typeCode": 1,
            "roadId": 13,
            "inLink": true,
            "laneCount": 2,
            "laneNumber": 0,
            "laneTypeName": "机动车道",
            "angle": 228.88,
            "speed": 12.17,
            "Speed": 43.83,
            "size": [
                4.05,
                1.82,
                2
            ],
            "color": "#FFFFFF",
            "x": 151.69,
            "y": 247.88,
            "z": 0.0,
            "xOrig": 457622.85,
            "yOrig": 2711307.07,
            "zOrig": 0.0,
            "longitude": null,
            "latitude": null,
            "eulerX": -2.42387,
            "eulerY": -2.42387,
            "eulerZ": -2.42387
        },
        {
            "id": 100005,
            "name": "",
            "typeCode": 1,
            "roadId": 13,
            "inLink": true,
            "laneCount": 2,
            "laneNumber": 1,
            "laneTypeName": "机动车道",
            "angle": 228.86,
            "speed": 13.73,
            "Speed": 49.44,
            "size": [
                4.07,
                1.83,
                2
            ],
            "color": "#FFFFFF",
            "x": 142.17,
            "y": 234.19,
            "z": 0.0,
            "xOrig": 457613.33,
            "yOrig": 2711293.38,
            "zOrig": 0.0,
            "longitude": null,
            "latitude": null,
            "eulerX": -2.42348,
            "eulerY": -2.42348,
            "eulerZ": -2.42348
        },
        {
            "id": 200005,
            "name": "",
            "typeCode": 1,
            "roadId": 5,
            "inLink": true,
            "laneCount": 2,
            "laneNumber": 1,
            "laneTypeName": "机动车道",
            "angle": 53.69,
            "speed": 14.59,
            "Speed": 52.52,
            "size": [
                4.78,
                2.11,
                2
            ],
            "color": "#A0A0A4",
            "x": -576.43,
            "y": -397.24,
            "z": 0.0,
            "xOrig": 456894.73,
            "yOrig": 2710661.95,
            "zOrig": 0.0,
            "longitude": null,
            "latitude": null,
            "eulerX": 0.63367,
            "eulerY": 0.63367,
            "eulerZ": 0.63367
        },
        {
            "id": 100006,
            "name": "",
            "typeCode": 1,
            "roadId": 13,
            "inLink": true,
            "laneCount": 2,
            "laneNumber": 0,
            "laneTypeName": "机动车道",
            "angle": 228.88,
            "speed": 12.0,
            "Speed": 43.19,
            "size": [
                4.89,
                2.16,
                2
            ],
            "color": "#FFFFFF",
            "x": 170.91,
            "y": 264.65,
            "z": 0.0,
            "xOrig": 457642.07,
            "yOrig": 2711323.84,
            "zOrig": 0.0,
            "longitude": null,
            "latitude": null,
            "eulerX": -2.42387,
            "eulerY": -2.42387,
            "eulerZ": -2.42387
        },
        {
            "id": 100007,
            "name": "",
            "typeCode": 1,
            "roadId": 13,
            "inLink": true,
            "laneCount": 2,
            "laneNumber": 1,
            "laneTypeName": "机动车道",
            "angle": 228.86,
            "speed": 13.3,
            "Speed": 47.88,
            "size": [
                4.62,
                2.05,
                2
            ],
            "color": "#EEAD0E",
            "x": 164.81,
            "y": 253.97,
            "z": 0.0,
            "xOrig": 457635.97,
            "yOrig": 2711313.16,
            "zOrig": 0.0,
            "longitude": null,
            "latitude": null,
            "eulerX": -2.42348,
            "eulerY": -2.42348,
            "eulerZ": -2.42348
        },
        {
            "id": 200006,
            "name": "",
            "typeCode": 1,
            "roadId": 5,
            "inLink": true,
            "laneCount": 2,
            "laneNumber": 0,
            "laneTypeName": "机动车道",
            "angle": 53.46,
            "speed": 13.41,
            "Speed": 48.26,
            "size": [
                4.46,
                1.98,
                2
            ],
            "color": "#A0A0A4",
            "x": -597.01,
            "y": -417.42,
            "z": 0.0,
            "xOrig": 456874.15,
            "yOrig": 2710641.77,
            "zOrig": 0.0,
            "longitude": null,
            "latitude": null,
            "eulerX": 0.63783,
            "eulerY": 0.63783,
            "eulerZ": 0.63783
        },
        {
            "id": 200007,
            "name": "",
            "typeCode": 1,
            "roadId": 5,
            "inLink": true,
            "laneCount": 2,
            "laneNumber": 1,
            "laneTypeName": "机动车道",
            "angle": 53.69,
            "speed": 13.9,
            "Speed": 50.04,
            "size": [
                4.46,
                1.99,
                2
            ],
            "color": "#EEAD0E",
            "x": -604.66,
            "y": -417.99,
            "z": 0.0,
            "xOrig": 456866.5,
            "yOrig": 2710641.2,
            "zOrig": 0.0,
            "longitude": null,
            "latitude": null,
            "eulerX": 0.63367,
            "eulerY": 0.63367,
            "eulerZ": 0.63367
        },
        {
            "id": 200008,
            "name": "",
            "typeCode": 1,
            "roadId": 5,
            "inLink": true,
            "laneCount": 2,
            "laneNumber": 0,
            "laneTypeName": "机动车道",
            "angle": 55.68,
            "speed": 13.09,
            "Speed": 47.12,
            "size": [
                4.81,
                2.12,
                2
            ],
            "color": "#EEAD0E",
            "x": -620.19,
            "y": -434.19,
            "z": 0.0,
            "xOrig": 456850.97,
            "yOrig": 2710625.0,
            "zOrig": 0.0,
            "longitude": null,
            "latitude": null,
            "eulerX": 0.59891,
            "eulerY": 0.59891,
            "eulerZ": 0.59891
        },
        {
            "id": 100008,
            "name": "",
            "typeCode": 1,
            "roadId": 13,
            "inLink": true,
            "laneCount": 2,
            "laneNumber": 1,
            "laneTypeName": "机动车道",
            "angle": 228.86,
            "speed": 12.62,
            "Speed": 45.43,
            "size": [
                4.46,
                1.99,
                2
            ],
            "color": "#A0A0A4",
            "x": 186.42,
            "y": 272.85,
            "z": 0.0,
            "xOrig": 457657.58,
            "yOrig": 2711332.04,
            "zOrig": 0.0,
            "longitude": null,
            "latitude": null,
            "eulerX": -2.42348,
            "eulerY": -2.42348,
            "eulerZ": -2.42348
        },
        {
            "id": 100009,
            "name": "",
            "typeCode": 1,
            "roadId": 13,
            "inLink": true,
            "laneCount": 2,
            "laneNumber": 1,
            "laneTypeName": "机动车道",
            "angle": 228.86,
            "speed": 11.9,
            "Speed": 42.85,
            "size": [
                4.58,
                2.03,
                2
            ],
            "color": "#FFFFFF",
            "x": 205.89,
            "y": 289.87,
            "z": 0.0,
            "xOrig": 457677.05,
            "yOrig": 2711349.06,
            "zOrig": 0.0,
            "longitude": null,
            "latitude": null,
            "eulerX": -2.42348,
            "eulerY": -2.42348,
            "eulerZ": -2.42348
        },
        {
            "id": 200009,
            "name": "",
            "typeCode": 1,
            "roadId": 5,
            "inLink": true,
            "laneCount": 2,
            "laneNumber": 1,
            "laneTypeName": "机动车道",
            "angle": 55.48,
            "speed": 13.21,
            "Speed": 47.54,
            "size": [
                4.49,
                1.99,
                2
            ],
            "color": "#FFFFFF",
            "x": -629.81,
            "y": -435.84,
            "z": 0.0,
            "xOrig": 456841.35,
            "yOrig": 2710623.35,
            "zOrig": 0.0,
            "longitude": null,
            "latitude": null,
            "eulerX": 0.60251,
            "eulerY": 0.60251,
            "eulerZ": 0.60251
        },
        {
            "id": 200010,
            "name": "",
            "typeCode": 1,
            "roadId": 5,
            "inLink": true,
            "laneCount": 2,
            "laneNumber": 0,
            "laneTypeName": "机动车道",
            "angle": 55.68,
            "speed": 12.57,
            "Speed": 45.26,
            "size": [
                4.66,
                2.06,
                2
            ],
            "color": "#EEAD0E",
            "x": -643.11,
            "y": -449.84,
            "z": 0.0,
            "xOrig": 456828.05,
            "yOrig": 2710609.35,
            "zOrig": 0.0,
            "longitude": null,
            "latitude": null,
            "eulerX": 0.59891,
            "eulerY": 0.59891,
            "eulerZ": 0.59891
        },
        {
            "id": 200011,
            "name": "",
            "typeCode": 1,
            "roadId": 5,
            "inLink": true,
            "laneCount": 2,
            "laneNumber": 1,
            "laneTypeName": "机动车道",
            "angle": 55.48,
            "speed": 12.7,
            "Speed": 45.73,
            "size": [
                4.97,
                2.19,
                2
            ],
            "color": "#FFFFFF",
            "x": -652.23,
            "y": -451.26,
            "z": 0.0,
            "xOrig": 456818.93,
            "yOrig": 2710607.93,
            "zOrig": 0.0,
            "longitude": null,
            "latitude": null,
            "eulerX": 0.60251,
            "eulerY": 0.60251,
            "eulerZ": 0.60251
        },
        {
            "id": 200012,
            "name": "",
            "typeCode": 2,
            "roadId": 5,
            "inLink": true,
            "laneCount": 2,
            "laneNumber": 0,
            "laneTypeName": "机动车道",
            "angle": 52.75,
            "speed": 11.02,
            "Speed": 39.68,
            "size": [
                11.63,
                2.35,
                2
            ],
            "color": "#A0A0A4",
            "x": -670.35,
            "y": -469.2,
            "z": 0.0,
            "xOrig": 456800.81,
            "yOrig": 2710589.99,
            "zOrig": 0.0,
            "longitude": null,
            "latitude": null,
            "eulerX": 0.65022,
            "eulerY": 0.65022,
            "eulerZ": 0.65022
        },
        {
            "id": 100010,
            "name": "",
            "typeCode": 1,
            "roadId": 13,
            "inLink": true,
            "laneCount": 2,
            "laneNumber": 0,
            "laneTypeName": "机动车道",
            "angle": 228.88,
            "speed": 11.54,
            "Speed": 41.53,
            "size": [
                4.12,
                1.85,
                2
            ],
            "color": "#EEAD0E",
            "x": 191.55,
            "y": 282.67,
            "z": 0.0,
            "xOrig": 457662.71,
            "yOrig": 2711341.86,
            "zOrig": 0.0,
            "longitude": null,
            "latitude": null,
            "eulerX": -2.42387,
            "eulerY": -2.42387,
            "eulerZ": -2.42387
        },
        {
            "id": 200013,
            "name": "",
            "typeCode": 1,
            "roadId": 5,
            "inLink": true,
            "laneCount": 2,
            "laneNumber": 1,
            "laneTypeName": "机动车道",
            "angle": 52.7,
            "speed": 11.42,
            "Speed": 41.11,
            "size": [
                4.08,
                1.83,
                2
            ],
            "color": "#FFFFFF",
            "x": -673.99,
            "y": -466.99,
            "z": 0.0,
            "xOrig": 456797.17,
            "yOrig": 2710592.2,
            "zOrig": 0.0,
            "longitude": null,
            "latitude": null,
            "eulerX": 0.65109,
            "eulerY": 0.65109,
            "eulerZ": 0.65109
        },
        {
            "id": 100011,
            "name": "",
            "typeCode": 1,
            "roadId": 13,
            "inLink": true,
            "laneCount": 2,
            "laneNumber": 1,
            "laneTypeName": "机动车道",
            "angle": 228.86,
            "speed": 11.06,
            "Speed": 39.81,
            "size": [
                4.75,
                2.1,
                2
            ],
            "color": "#FFFFFF",
            "x": 223.81,
            "y": 305.52,
            "z": 0.0,
            "xOrig": 457694.97,
            "yOrig": 2711364.71,
            "zOrig": 0.0,
            "longitude": null,
            "latitude": null,
            "eulerX": -2.42348,
            "eulerY": -2.42348,
            "eulerZ": -2.42348
        },
        {
            "id": 200014,
            "name": "",
            "typeCode": 1,
            "roadId": 5,
            "inLink": true,
            "laneCount": 2,
            "laneNumber": 0,
            "laneTypeName": "机动车道",
            "angle": 47.97,
            "speed": 10.12,
            "Speed": 36.44,
            "size": [
                4.39,
                1.96,
                2
            ],
            "color": "#EEAD0E",
            "x": -689.76,
            "y": -485.68,
            "z": 0.0,
            "xOrig": 456781.4,
            "yOrig": 2710573.51,
            "zOrig": 0.0,
            "longitude": null,
            "latitude": null,
            "eulerX": 0.73359,
            "eulerY": 0.73359,
            "eulerZ": 0.73359
        },
        {
            "id": 100012,
            "name": "",
            "typeCode": 2,
            "roadId": 13,
            "inLink": true,
            "laneCount": 2,
            "laneNumber": 0,
            "laneTypeName": "机动车道",
            "angle": 228.88,
            "speed": 10.45,
            "Speed": 37.63,
            "size": [
                11.53,
                2.3,
                2
            ],
            "color": "#EEAD0E",
            "x": 214.79,
            "y": 302.96,
            "z": 0.0,
            "xOrig": 457685.95,
            "yOrig": 2711362.15,
            "zOrig": 0.0,
            "longitude": null,
            "latitude": null,
            "eulerX": -2.42387,
            "eulerY": -2.42387,
            "eulerZ": -2.42387
        },
        {
            "id": 100013,
            "name": "",
            "typeCode": 1,
            "roadId": 13,
            "inLink": true,
            "laneCount": 2,
            "laneNumber": 0,
            "laneTypeName": "机动车道",
            "angle": 228.88,
            "speed": 9.54,
            "Speed": 34.35,
            "size": [
                4.12,
                1.85,
                2
            ],
            "color": "#EEAD0E",
            "x": 233.13,
            "y": 318.98,
            "z": 0.0,
            "xOrig": 457704.29,
            "yOrig": 2711378.17,
            "zOrig": 0.0,
            "longitude": null,
            "latitude": null,
            "eulerX": -2.42387,
            "eulerY": -2.42387,
            "eulerZ": -2.42387
        },
        {
            "id": 100014,
            "name": "",
            "typeCode": 1,
            "roadId": 13,
            "inLink": true,
            "laneCount": 2,
            "laneNumber": 1,
            "laneTypeName": "机动车道",
            "angle": 228.86,
            "speed": 9.79,
            "Speed": 35.23,
            "size": [
                4.87,
                2.15,
                2
            ],
            "color": "#EEAD0E",
            "x": 240.12,
            "y": 319.77,
            "z": 0.0,
            "xOrig": 457711.28,
            "yOrig": 2711378.96,
            "zOrig": 0.0,
            "longitude": null,
            "latitude": null,
            "eulerX": -2.42348,
            "eulerY": -2.42348,
            "eulerZ": -2.42348
        },
        {
            "id": 200015,
            "name": "",
            "typeCode": 1,
            "roadId": 5,
            "inLink": true,
            "laneCount": 2,
            "laneNumber": 1,
            "laneTypeName": "机动车道",
            "angle": 47.48,
            "speed": 10.45,
            "Speed": 37.61,
            "size": [
                4.48,
                1.99,
                2
            ],
            "color": "#EEAD0E",
            "x": -690.96,
            "y": -481.49,
            "z": 0.0,
            "xOrig": 456780.2,
            "yOrig": 2710577.7,
            "zOrig": 0.0,
            "longitude": null,
            "latitude": null,
            "eulerX": 0.74218,
            "eulerY": 0.74218,
            "eulerZ": 0.74218
        },
        {
            "id": 100015,
            "name": "",
            "typeCode": 1,
            "roadId": 13,
            "inLink": true,
            "laneCount": 2,
            "laneNumber": 1,
            "laneTypeName": "机动车道",
            "angle": 228.86,
            "speed": 7.82,
            "Speed": 28.16,
            "size": [
                4.55,
                2.02,
                2
            ],
            "color": "#FFFFFF",
            "x": 253.61,
            "y": 331.56,
            "z": 0.0,
            "xOrig": 457724.77,
            "yOrig": 2711390.75,
            "zOrig": 0.0,
            "longitude": null,
            "latitude": null,
            "eulerX": -2.42348,
            "eulerY": -2.42348,
            "eulerZ": -2.42348
        },
        {
            "id": 200016,
            "name": "",
            "typeCode": 1,
            "roadId": 5,
            "inLink": true,
            "laneCount": 2,
            "laneNumber": 1,
            "laneTypeName": "机动车道",
            "angle": 42.12,
            "speed": 8.96,
            "Speed": 32.24,
            "size": [
                4.04,
                1.81,
                2
            ],
            "color": "#FFFFFF",
            "x": -704.75,
            "y": -495.32,
            "z": 0.0,
            "xOrig": 456766.41,
            "yOrig": 2710563.87,
            "zOrig": 0.0,
            "longitude": null,
            "latitude": null,
            "eulerX": 0.83572,
            "eulerY": 0.83572,
            "eulerZ": 0.83572
        },
        {
            "id": 200017,
            "name": "",
            "typeCode": 1,
            "roadId": 5,
            "inLink": true,
            "laneCount": 2,
            "laneNumber": 0,
            "laneTypeName": "机动车道",
            "angle": 42.12,
            "speed": 8.78,
            "Speed": 31.61,
            "size": [
                4.98,
                2.19,
                2
            ],
            "color": "#EEAD0E",
            "x": -703.66,
            "y": -499.92,
            "z": 0.0,
            "xOrig": 456767.5,
            "yOrig": 2710559.27,
            "zOrig": 0.0,
            "longitude": null,
            "latitude": null,
            "eulerX": 0.83572,
            "eulerY": 0.83572,
            "eulerZ": 0.83572
        },
        {
            "id": 200018,
            "name": "",
            "typeCode": 1,
            "roadId": 5,
            "inLink": true,
            "laneCount": 2,
            "laneNumber": 1,
            "laneTypeName": "机动车道",
            "angle": 38.26,
            "speed": 7.01,
            "Speed": 25.25,
            "size": [
                5.0,
                2.2,
                2
            ],
            "color": "#FFFFFF",
            "x": -715.87,
            "y": -507.75,
            "z": 0.0,
            "xOrig": 456755.29,
            "yOrig": 2710551.44,
            "zOrig": 0.0,
            "longitude": null,
            "latitude": null,
            "eulerX": 0.9031,
            "eulerY": 0.9031,
            "eulerZ": 0.9031
        },
        {
            "id": 100016,
            "name": "",
            "typeCode": 1,
            "roadId": 13,
            "inLink": true,
            "laneCount": 2,
            "laneNumber": 0,
            "laneTypeName": "机动车道",
            "angle": 228.88,
            "speed": 8.39,
            "Speed": 30.2,
            "size": [
                4.3,
                1.92,
                2
            ],
            "color": "#A0A0A4",
            "x": 246.91,
            "y": 331.01,
            "z": 0.0,
            "xOrig": 457718.07,
            "yOrig": 2711390.2,
            "zOrig": 0.0,
            "longitude": null,
            "latitude": null,
            "eulerX": -2.42387,
            "eulerY": -2.42387,
            "eulerZ": -2.42387
        },
        {
            "id": 100018,
            "name": "",
            "typeCode": 1,
            "roadId": 13,
            "inLink": true,
            "laneCount": 2,
            "laneNumber": 0,
            "laneTypeName": "机动车道",
            "angle": 228.88,
            "speed": 7.54,
            "Speed": 27.15,
            "size": [
                4.38,
                1.95,
                2
            ],
            "color": "#A0A0A4",
            "x": 258.82,
            "y": 341.41,
            "z": 0.0,
            "xOrig": 457729.98,
            "yOrig": 2711400.6,
            "zOrig": 0.0,
            "longitude": null,
            "latitude": null,
            "eulerX": -2.42387,
            "eulerY": -2.42387,
            "eulerZ": -2.42387
        }
    ]
}